fronius_solarweb/__init__.py
fronius_solarweb/api.py
fronius_solarweb/errors.py
fronius_solarweb/schema/__init__.py
fronius_solarweb/schema/device.py
fronius_solarweb/schema/error.py
fronius_solarweb/schema/hist.py
fronius_solarweb/schema/pvsystem.py
fronius_solarweb/schema/service.py
fronius_solarweb-0.4.0.dist-info/LICENSE
fronius_solarweb-0.4.0.dist-info/METADATA
fronius_solarweb-0.4.0.dist-info/WHEEL
fronius_solarweb-0.4.0.dist-info/RECORD
