Metadata-Version: 2.3
Name: fronius_solarweb
Version: 0.4.0
Summary: A Python wrapper for the Fronius Solar.web Cloud API
License: MIT
Author: Derek Caudwell
Author-email: derek_caudwell@hotmail.com
Requires-Python: >=3.10
Classifier: License :: OSI Approved :: MIT License
Classifier: Programming Language :: Python :: 3
Classifier: Programming Language :: Python :: 3.10
Classifier: Programming Language :: Python :: 3.11
Classifier: Programming Language :: Python :: 3.12
Classifier: Programming Language :: Python :: 3.13
Requires-Dist: httpx (>=0.23)
Requires-Dist: pydantic (>=2,<3.0)
Requires-Dist: tenacity (>=8.1,<10.0)
Project-URL: Repository, https://github.com/drc38/python-fronius-web
Project-URL: issues, https://github.com/drc38/python-fronius-web/issues
